[
  {
    "id": "001",
    "pCode": "B123451",
    "pName": "Bed Sheet",
    "status": "Low Stock",
    "price": "12",
    "category": "Room Service",
    "qty": "12"
  },
  {
    "id": "002",
    "pCode": "T654321",
    "pName": "Towel",
    "status": "In Stock",
    "price": "8",
    "category": "Bathroom Supplies",
    "qty": "50"
  },
  {
    "id": "003",
    "pCode": "P789012",
    "pName": "Pillow",
    "status": "Out of Stock",
    "price": "15",
    "category": "Room Service",
    "qty": "0"
  },
  {
    "id": "004",
    "pCode": "S345678",
    "pName": "Shampoo",
    "status": "Low Stock",
    "price": "5",
    "category": "Bathroom Supplies",
    "qty": "10"
  },
  {
    "id": "005",
    "pCode": "S987654",
    "pName": "Soap",
    "status": "In Stock",
    "price": "3",
    "category": "Bathroom Supplies",
    "qty": "100"
  },
  {
    "id": "006",
    "pCode": "C123987",
    "pName": "Coffee",
    "status": "In Stock",
    "price": "2",
    "category": "Beverages",
    "qty": "200"
  },
  {
    "id": "007",
    "pCode": "T564738",
    "pName": "Tea Bags",
    "status": "In Stock",
    "price": "1",
    "category": "Beverages",
    "qty": "300"
  },
  {
    "id": "008",
    "pCode": "H135792",
    "pName": "Hand Sanitizer",
    "status": "Low Stock",
    "price": "6",
    "category": "Health & Safety",
    "qty": "20"
  },
  {
    "id": "009",
    "pCode": "K246810",
    "pName": "Keycard",
    "status": "In Stock",
    "price": "1",
    "category": "Room Service",
    "qty": "500"
  },
  {
    "id": "010",
    "pCode": "B111213",
    "pName": "Bathrobe",
    "status": "In Stock",
    "price": "25",
    "category": "Room Service",
    "qty": "30"
  },
  {
    "id": "011",
    "pCode": "G314159",
    "pName": "Glass Cleaner",
    "status": "In Stock",
    "price": "4",
    "category": "Cleaning Supplies",
    "qty": "40"
  },
  {
    "id": "012",
    "pCode": "D217364",
    "pName": "Dish Soap",
    "status": "In Stock",
    "price": "3",
    "category": "Cleaning Supplies",
    "qty": "80"
  },
  {
    "id": "013",
    "pCode": "R948372",
    "pName": "Remote Control",
    "status": "Low Stock",
    "price": "10",
    "category": "Electronics",
    "qty": "15"
  },
  {
    "id": "014",
    "pCode": "L627381",
    "pName": "Light Bulb",
    "status": "In Stock",
    "price": "2",
    "category": "Maintenance Supplies",
    "qty": "100"
  },
  {
    "id": "015",
    "pCode": "C134567",
    "pName": "Conditioner",
    "status": "Low Stock",
    "price": "5",
    "category": "Bathroom Supplies",
    "qty": "10"
  },
  {
    "id": "016",
    "pCode": "N657483",
    "pName": "Napkin",
    "status": "In Stock",
    "price": "1",
    "category": "Dining Supplies",
    "qty": "500"
  },
  {
    "id": "017",
    "pCode": "F273849",
    "pName": "Face Mask",
    "status": "In Stock",
    "price": "1",
    "category": "Health & Safety",
    "qty": "200"
  }
]
